<?xml version="1.0" encoding="UTF-8"?>
<MetaDataObject xmlns="http://v8.1c.ru/8.3/MDClasses" xmlns:app="http://v8.1c.ru/8.2/managed-application/core" xmlns:cfg="http://v8.1c.ru/8.1/data/enterprise/current-config" xmlns:cmi="http://v8.1c.ru/8.2/managed-application/cmi" xmlns:ent="http://v8.1c.ru/8.1/data/enterprise" xmlns:lf="http://v8.1c.ru/8.2/managed-application/logform" xmlns:style="http://v8.1c.ru/8.1/data/ui/style" xmlns:sys="http://v8.1c.ru/8.1/data/ui/fonts/system" xmlns:v8="http://v8.1c.ru/8.1/data/core" xmlns:v8ui="http://v8.1c.ru/8.1/data/ui" xmlns:web="http://v8.1c.ru/8.1/data/ui/colors/web" xmlns:win="http://v8.1c.ru/8.1/data/ui/colors/windows" xmlns:xen="http://v8.1c.ru/8.3/xcf/enums" xmlns:xpr="http://v8.1c.ru/8.3/xcf/predef" xmlns:xr="http://v8.1c.ru/8.3/xcf/readable" xmlns:xs="http://www.w3.org/2001/XMLSchema" xmlns:xsi="http://www.w3.org/2001/XMLSchema-instance" version="2.12">
	<Constant uuid="2a5f595d-19a5-4794-a959-bb53702673f3">
		<InternalInfo>
			<xr:GeneratedType name="ConstantManager.ДатаОкончанияПереходаНаСтандартIBAN" category="Manager">
				<xr:TypeId>f0c93df1-b39c-434b-a36a-00bd630c946a</xr:TypeId>
				<xr:ValueId>7454a9d8-795e-49a1-b6de-3986743a9755</xr:ValueId>
			</xr:GeneratedType>
			<xr:GeneratedType name="ConstantValueManager.ДатаОкончанияПереходаНаСтандартIBAN" category="ValueManager">
				<xr:TypeId>c27daf7d-c2a4-4d71-b014-2144fa948887</xr:TypeId>
				<xr:ValueId>124f5bb8-3570-4edf-ba98-ba982e0c243f</xr:ValueId>
			</xr:GeneratedType>
			<xr:GeneratedType name="ConstantValueKey.ДатаОкончанияПереходаНаСтандартIBAN" category="ValueKey">
				<xr:TypeId>d96eb1fe-d023-4340-96fb-3a002fee9f71</xr:TypeId>
				<xr:ValueId>3821dc9a-60ec-4fe1-ba31-7da753ffac17</xr:ValueId>
			</xr:GeneratedType>
		</InternalInfo>
		<Properties>
			<Name>ДатаОкончанияПереходаНаСтандартIBAN</Name>
			<Synonym>
				<v8:item>
					<v8:lang>ru</v8:lang>
					<v8:content>Дата окончания перевода номеров банковских счетов на стандарт IBAN согласно постановлению НБУ № 162 від 28.12.2018</v8:content>
				</v8:item>
				<v8:item>
					<v8:lang>uk</v8:lang>
					<v8:content>Дата закінчення переведення номерів банківських рахунків на стандарт IBAN згідно з постановою НБУ № 162 від 28.12.2018</v8:content>
				</v8:item>
			</Synonym>
			<Comment>по-умолчанию 31.10.2019 (если константа не заполнена)</Comment>
			<Type>
				<v8:Type>xs:dateTime</v8:Type>
				<v8:DateQualifiers>
					<v8:DateFractions>Date</v8:DateFractions>
				</v8:DateQualifiers>
			</Type>
			<UseStandardCommands>false</UseStandardCommands>
			<DefaultForm/>
			<ExtendedPresentation/>
			<Explanation/>
			<PasswordMode>false</PasswordMode>
			<Format/>
			<EditFormat/>
			<ToolTip/>
			<MarkNegatives>false</MarkNegatives>
			<Mask/>
			<MultiLine>false</MultiLine>
			<ExtendedEdit>false</ExtendedEdit>
			<MinValue xsi:nil="true"/>
			<MaxValue xsi:nil="true"/>
			<FillChecking>DontCheck</FillChecking>
			<ChoiceFoldersAndItems>Items</ChoiceFoldersAndItems>
			<ChoiceParameterLinks/>
			<ChoiceParameters/>
			<QuickChoice>Auto</QuickChoice>
			<ChoiceForm/>
			<LinkByType/>
			<ChoiceHistoryOnInput>Auto</ChoiceHistoryOnInput>
			<DataLockControlMode>Managed</DataLockControlMode>
			<DataHistory>DontUse</DataHistory>
			<UpdateDataHistoryImmediatelyAfterWrite>false</UpdateDataHistoryImmediatelyAfterWrite>
			<ExecuteAfterWriteDataHistoryVersionProcessing>false</ExecuteAfterWriteDataHistoryVersionProcessing>
		</Properties>
	</Constant>
</MetaDataObject>